odoo/addons/document_page_health_safety_manual/README.rst
odoo/addons/document_page_health_safety_manual/__init__.py
odoo/addons/document_page_health_safety_manual/__manifest__.py
odoo/addons/document_page_health_safety_manual/data/document_page.xml
odoo/addons/document_page_health_safety_manual/i18n/document_page_health_safety_manual.pot
odoo/addons/document_page_health_safety_manual/i18n/it.po
odoo/addons/document_page_health_safety_manual/readme/CONTRIBUTORS.md
odoo/addons/document_page_health_safety_manual/readme/DESCRIPTION.md
odoo/addons/document_page_health_safety_manual/readme/ROADMAP.md
odoo/addons/document_page_health_safety_manual/readme/USAGE.md
odoo/addons/document_page_health_safety_manual/static/description/icon.png
odoo/addons/document_page_health_safety_manual/static/description/index.html
odoo_addon_document_page_health_safety_manual-18.0.1.0.1.dist-info/METADATA
odoo_addon_document_page_health_safety_manual-18.0.1.0.1.dist-info/WHEEL
odoo_addon_document_page_health_safety_manual-18.0.1.0.1.dist-info/top_level.txt
odoo_addon_document_page_health_safety_manual-18.0.1.0.1.dist-info/RECORD
